genestack_client/__init__.py
genestack_client/bio_meta_keys.py
genestack_client/bio_metainfo.py
genestack_client/chunked_upload.py
genestack_client/cla.py
genestack_client/data_flow_editor.py
genestack_client/data_importer.py
genestack_client/datasets_util.py
genestack_client/expression_navigator.py
genestack_client/file_filters.py
genestack_client/file_initializer.py
genestack_client/file_permissions.py
genestack_client/file_types.py
genestack_client/files_util.py
genestack_client/genestack_connection.py
genestack_client/genestack_exceptions.py
genestack_client/genestack_metainfo.py
genestack_client/genestack_shell.py
genestack_client/genome_query.py
genestack_client/groups_util.py
genestack_client/metainfo_scalar_values.py
genestack_client/samples.py
genestack_client/sudo_utils.py
genestack_client/task_log_viewer.py
genestack_client/unaligned_reads.py
genestack_client/utils.py
genestack_client/version.py
genestack_client/scripts/__init__.py
genestack_client/scripts/genestack_application_manager.py
genestack_client/scripts/genestack_uploader.py
genestack_client/scripts/genestack_user_setup.py
genestack_client/scripts/shell.py
genestack_client/settings/__init__.py
genestack_client/settings/genestack_config.py
genestack_client/settings/genestack_user.py
genestack_client-0.24.0a1.dist-info/METADATA
genestack_client-0.24.0a1.dist-info/RECORD
genestack_client-0.24.0a1.dist-info/WHEEL
genestack_client-0.24.0a1.dist-info/entry_points.txt
genestack_client-0.24.0a1.dist-info/top_level.txt
